payme/__init__.py
payme/admin.py
payme/apps.py
payme/const.py
payme/licensing.py
payme/models.py
payme/urls.py
payme/util.py
payme/classes/__init__.py
payme/classes/cards.py
payme/classes/client.py
payme/classes/http.py
payme/classes/initializer.py
payme/classes/receipts.py
payme/exceptions/__init__.py
payme/exceptions/general.py
payme/exceptions/webhook.py
payme/migrations/0001_initial.py
payme/migrations/0002_paymetransactions_fiscal_data.py
payme/migrations/0003_alter_paymetransactions_fiscal_data.py
payme/migrations/0004_alter_paymetransactions_account_id.py
payme/migrations/0005_alter_paymetransactions_amount.py
payme/migrations/__init__.py
payme/type_definitions/__init__.py
payme/type_definitions/request/__init__.py
payme/type_definitions/response/__init__.py
payme/type_definitions/response/cards.py
payme/type_definitions/response/receipts.py
payme/type_definitions/response/webhook.py
payme/views/__init__.py
payme/views/base.py
payme/views/payme.py
payme_pkg_clone-1.0.1.dist-info/METADATA
payme_pkg_clone-1.0.1.dist-info/WHEEL
payme_pkg_clone-1.0.1.dist-info/top_level.txt
payme_pkg_clone-1.0.1.dist-info/RECORD
