Metadata-Version: 2.4
Name: payme-pkg-clone
Version: 1.0.1
Summary: Python package for Payme (Paycom) payment integration
Author-email: Muhammadvadud <gmuhammadvadud@gmail.com>
License: MIT
Keywords: payme,paycom,payment,uzbekistan,django
Classifier: Development Status :: 4 - Beta
Classifier: Intended Audience :: Developers
Classifier: License :: OSI Approved :: MIT License
Classifier: Programming Language :: Python :: 3
Classifier: Programming Language :: Python :: 3.7
Classifier: Programming Language :: Python :: 3.8
Classifier: Programming Language :: Python :: 3.9
Classifier: Programming Language :: Python :: 3.10
Classifier: Programming Language :: Python :: 3.11
Classifier: Programming Language :: Python :: 3.12
Classifier: Framework :: Django
Classifier: Topic :: Software Development :: Libraries :: Python Modules
Requires-Python: >=3.7
Requires-Dist: Django>=3.0
Requires-Dist: requests>=2.25.0
Requires-Dist: djangorestframework>=3.12.0
